visionpy/__init__.py
visionpy/anndata.py
visionpy/api.py
visionpy/blueprint.py
visionpy/diffexp.py
visionpy/signature.py
visionpy/static/whitelist.txt
visionpy/static/css/favicon.png
visionpy/static/css/loading.svg
visionpy/static/css/logo_HorizontalLogo.svg
visionpy/static/css/lower_left_content.css
visionpy/static/css/right_content.css
visionpy/static/css/styles.css
visionpy/static/css/upper_left_content.css
visionpy/static/src/Clustered_HeatMap.js
visionpy/static/src/ColorScatterPlotly.js
visionpy/static/src/PhyloPlotly.js
visionpy/static/src/Utilities.js
visionpy/static/src/api.js
visionpy/static/src/lower_left_content.js
visionpy/static/src/main.js
visionpy/static/src/misc.js
visionpy/static/src/right_content.js
visionpy/static/src/upper_left_content.js
visionpy/static/thirdparty/bootstrap/bootstrap.bundle.min.js
visionpy/static/thirdparty/bootstrap/bootstrap.min.css
visionpy/static/thirdparty/chosen/chosen-sprite.png
visionpy/static/thirdparty/chosen/chosen-sprite@2x.png
visionpy/static/thirdparty/chosen/chosen.jquery.min.js
visionpy/static/thirdparty/chosen/chosen.min.css
visionpy/static/thirdparty/d3/d3.min.js
visionpy/static/thirdparty/d3/d3tip.js
visionpy/static/thirdparty/datatables/datatables.min.css
visionpy/static/thirdparty/datatables/datatables.min.js
visionpy/static/thirdparty/datatables/DataTables-1.10.18/images/sort_asc.png
visionpy/static/thirdparty/datatables/DataTables-1.10.18/images/sort_asc_disabled.png
visionpy/static/thirdparty/datatables/DataTables-1.10.18/images/sort_both.png
visionpy/static/thirdparty/datatables/DataTables-1.10.18/images/sort_desc.png
visionpy/static/thirdparty/datatables/DataTables-1.10.18/images/sort_desc_disabled.png
visionpy/static/thirdparty/hsluv/hsluv-0.1.0.min.js
visionpy/static/thirdparty/jquery/jquery-2.1.4.min.js
visionpy/static/thirdparty/jszip/jszip.min.js
visionpy/static/thirdparty/lodash/lodash.min.js
visionpy/static/thirdparty/plotly/plotly.min.js
visionpy/static/thirdparty/popper/popper.min.js
visionpy_sc-0.2.0.dist-info/METADATA
visionpy_sc-0.2.0.dist-info/WHEEL
visionpy_sc-0.2.0.dist-info/entry_points.txt
visionpy_sc-0.2.0.dist-info/licenses/LICENSE
visionpy_sc-0.2.0.dist-info/RECORD
