Metadata-Version: 2.1
Name: visionpy-sc
Version: 0.2.0
Summary: Signature Analysis and Visualization for Single-Cell RNA-seq
Project-URL: Documentation, https://visionpy.readthedocs.io/
Project-URL: Source, https://github.com/yoseflab/visionpy
Project-URL: Home-page, https://github.com/yoseflab/visionpy
Author: Adam Gayoso
Maintainer-email: Adam Gayoso <adamgayoso@berkeley.edu>
License: BSD 3-Clause License
License-File: LICENSE
Requires-Python: >=3.8
Requires-Dist: anndata
Requires-Dist: click
Requires-Dist: flask
Requires-Dist: flask-compress
Requires-Dist: leidenalg
Requires-Dist: rich
Requires-Dist: scanpy>=1.9
Provides-Extra: dev
Requires-Dist: bump2version; extra == 'dev'
Requires-Dist: pre-commit; extra == 'dev'
Provides-Extra: doc
Requires-Dist: ipykernel; extra == 'doc'
Requires-Dist: ipython; extra == 'doc'
Requires-Dist: myst-nb; extra == 'doc'
Requires-Dist: scanpydoc[typehints]>=0.7.4; extra == 'doc'
Requires-Dist: sphinx; extra == 'doc'
Requires-Dist: sphinx-book-theme>=1.0; extra == 'doc'
Requires-Dist: sphinx-copybutton; extra == 'doc'
Requires-Dist: sphinxcontrib-bibtex>=1.0.0; extra == 'doc'
Provides-Extra: test
Requires-Dist: black; extra == 'test'
Requires-Dist: flake8; extra == 'test'
Requires-Dist: pytest; extra == 'test'
Requires-Dist: pytest-cov; extra == 'test'
